{
  "bookshelf:load_conditions": [
    {
      "type": "bookshelf:item_exists",
      "values": [
        "pixelmon:amethyst_ore"
      ]
    }
  ],
  "type": "botanypots:crop",
  "input": {
    "item": "pixelmon:amethyst"
  },
  "soil": {
    "tag": "botany_pots_ore_planting:soil/amethyst"
  },
  "grow_time": 1200,
  "display": {
    "type": "botanypots:simple",
    "block_state": {
      "block": "pixelmon:amethyst_ore"
    }
  },
  "drops": [
    {
      "type": "botanypots:items",
      "items": [
        {
          "result": {
            "id": "pixelmon:amethyst"
          },
          "chance": 1.0
        }
      ]
    }
  ],
  "yield": 2.5,
  "yield_scale": 1.0
}
